{
    "2": "THPT Nguyễn Đình Chiểu",
    "4": "THPT Trần Văn Ơn",
    "5": "THPT Diệp Minh Châu",
    "7": "THPT  Trần Văn Kiết",
    "8": "THPT Trương Vĩnh Ký",
    "10": "THPT Cheguevara",
    "11": "THPT Ca Văn Thỉnh",
    "12": "THPT Bán công Mỏ Cày",
    "14": "THPT Phan Văn Trị",
    "15": "THPT Nguyễn Ngọc Thăng",
    "17": "THPT Lê Hoàng Chiếu",
    "18": "THPT Huỳnh Tấn Phát",
    "20": "THPT Phan Thanh Giản",
    "22": "THPT Lê Hoài Đôn",
    "23": "THPT Bán Công Thị Xã",
    "24": "THPT Ngô Văn Cấn",
    "25": "THPT Lê Qúy Đôn",
    "26": "THPT BC Châu Thành A",
    "27": "THPT BC Châu Thành B",
    "28": "THPT Dân lập Giồng Trôm",
    "29": "THPT Bán công Chợ Lách",
    "30": "THPT chuyên Bến Tre",
    "32": "THPT Bán công Bình Đại",
    "33": "THPT Bán công Thạnh Phú",
    "34": "THPT Bán công Vĩnh Thành",
    "35": "THPT Bán công Phước Mỹ Trung",
    "36": "THPT Bán công Ba Tri",
    "37": "THPT Bán công Lộc Thuận",
    "38": "THPT Tán Kế",
    "39": "THPT Bán công Giồng Trôm",
    "40": "THPT Võ Trường Toản",
    "41": "THPT Bán công An Thới",
    "42": "THPT Quản Trọng Hoàng",
    "43": "THPT  Trần Trường Sinh",
    "44": "THPT Đoàn Thị Điểm",
    "45": "Trung tâm GDTX thành phố Bến Tre",
    "46": "THPT Nguyễn Thị Minh Khai",
    "47": "THPT Sương Nguyệt Anh",
    "48": "THPT Lê Anh Xuân",
    "49": "THPT Mạc Đĩnh Chi",
    "50": "THPT Hermann Gmeiner",
    "51": "Trung cấp Y Tế Bến Tre",
    "54": "Trung tâm GDTX Châu Thành",
    "55": "Trung tâm GDTX Chợ Lách",
    "56": "Trung tâm GDTX huyện Mỏ Cày Nam",
    "57": "Trung tâm GDTX huyện Giồng Trôm",
    "58": "Trung tâm GDTX Bình  Đại",
    "59": "Trung tâm GDTX Ba Tri",
    "60": "Trung tâm GDTX Thạnh Phú",
    "61": "THPT Nguyễn Thị Định",
    "62": "CĐ Bến Tre",
    "63": "THPT Nguyễn Trãi",
    "64": "THPT Phan Ngọc Tòng",
    "66": "THPT Lạc Long Quân",
    "67": "THPT Nguyễn Huệ",
    "68": "CĐ nghề Đồng Khởi",
    "69": "TC nghề Bến Tre",
    "70": "Trung tâm GDTX Mỏ Cày Bắc",
    "71": "Trường THPT Phan Liêm"
}
